pyAbstracts/__init__.py
pyAbstracts/pyAbstracts.py
pyAbstracts-1.0.4.dist-info/METADATA
pyAbstracts-1.0.4.dist-info/WHEEL
pyAbstracts-1.0.4.dist-info/top_level.txt
pyAbstracts-1.0.4.dist-info/RECORD
