Metadata-Version: 2.1
Name: pyAbstracts
Version: 1.0.4
Summary: Abstract classes that can be extended
Home-page: UNKNOWN
Author: Alan Bacon
Author-email: alan@bacontowers.co.uk
License: UNKNOWN
Platform: UNKNOWN
